dsplayer_applemusic/__init__.py
dsplayer_applemusic/applemusic.py
dsplayer_applemusic-1.3.0.dist-info/LICENSE
dsplayer_applemusic-1.3.0.dist-info/METADATA
dsplayer_applemusic-1.3.0.dist-info/WHEEL
dsplayer_applemusic-1.3.0.dist-info/entry_points.txt
dsplayer_applemusic-1.3.0.dist-info/top_level.txt
dsplayer_applemusic-1.3.0.dist-info/RECORD
